{"_env":"NODEJS","_serializationMethod":"normal","_autosave":false,"_autosaveInterval":5000,"_collections":[{"name":"items","unindexedSortComparator":"js","defaultLokiOperatorPackage":"js","_dynamicViews":[],"uniqueNames":[],"transforms":{},"rangedIndexes":{},"_data":[{"slug":"bio","toc":[],"body":{"type":"root","children":[{"type":"element","tag":"p","props":{},"children":[{"type":"element","tag":"code","props":{},"children":[{"type":"text","value":"\"Only time between defeat and a new start matters\""}]}]},{"type":"text","value":"\n"},{"type":"element","tag":"p","props":{},"children":[{"type":"text","value":"Hey, my name is Ilya Fakhrutdinov. I grew up in Kazakhstan, but in 2015 I've decided to change my life.\nAnd in 2016, I took all my savings, bought a one-way flight ticket to Prague.\nIn February, 2016, I've started to learn Czech language with one goal on my mind, spend only five months\nto learn new language."}]},{"type":"text","value":"\n"},{"type":"element","tag":"p","props":{},"children":[{"type":"text","value":"It was a big challenge. But I did it."}]},{"type":"text","value":"\n"},{"type":"element","tag":"p","props":{},"children":[{"type":"text","value":"Next couple of months after language school, I spent deciding my next step.\nMy first degree in networks field, so I decided to enhance my knowledge, but from a different side,\nfrom a software side. I choose to get a degree in applied informatics,\nin College of Polytechnics in Jihlava, Czech Republic.\nMy thesis was a creation mobile application for hearing test for Android platform, and again it was a challenge\nfor me,\nbecause I programmed it in new language for me, Kotlin."}]},{"type":"text","value":"\n"},{"type":"element","tag":"p","props":{},"children":[{"type":"text","value":"I graduated in 2019"}]},{"type":"text","value":"\n"},{"type":"element","tag":"p","props":{},"children":[{"type":"text","value":"During my study, I found my first job as a Web Developer and it become my passion.\nI really like to be involved in interesting projects, where I can use and learn new technologies.\nI'm a team player, passion about my work. Always learning."}]},{"type":"text","value":"\n"},{"type":"element","tag":"p","props":{},"children":[{"type":"text","value":"Besides of developing, I like to read, play on the guitar and run."}]}]},"text":"`\"Only time between defeat and a new start matters\"`\n\nHey, my name is Ilya Fakhrutdinov. I grew up in Kazakhstan, but in 2015 I've decided to change my life.\nAnd in 2016, I took all my savings, bought a one-way flight ticket to Prague.\nIn February, 2016, I've started to learn Czech language with one goal on my mind, spend only five months\nto learn new language.\n      \nIt was a big challenge. But I did it.\n      \nNext couple of months after language school, I spent deciding my next step.\nMy first degree in networks field, so I decided to enhance my knowledge, but from a different side,\nfrom a software side. I choose to get a degree in applied informatics,\nin College of Polytechnics in Jihlava, Czech Republic.\nMy thesis was a creation mobile application for hearing test for Android platform, and again it was a challenge\nfor me,\nbecause I programmed it in new language for me, Kotlin.\n      \nI graduated in 2019\n      \nDuring my study, I found my first job as a Web Developer and it become my passion.\nI really like to be involved in interesting projects, where I can use and learn new technologies.\nI'm a team player, passion about my work. Always learning.\n\nBesides of developing, I like to read, play on the guitar and run.\n      \n","dir":"/","path":"/bio","extension":".md","createdAt":"2020-10-28T17:34:03.241Z","updatedAt":"2020-10-28T21:18:52.116Z","meta":{"version":0,"revision":0,"created":1604501935968},"$loki":1}],"idIndex":[1],"maxId":1,"_dirty":true,"_nestedProperties":[],"transactional":false,"asyncListeners":false,"disableMeta":false,"disableChangesApi":true,"disableDeltaChangesApi":true,"cloneObjects":false,"cloneMethod":"deep","changes":[],"_fullTextSearch":{"ii":{"title":{"_store":true,"_optimizeChanges":true,"docCount":0,"docStore":[],"totalFieldLength":0,"root":{}},"description":{"_store":true,"_optimizeChanges":true,"docCount":0,"docStore":[],"totalFieldLength":0,"root":{}},"slug":{"_store":true,"_optimizeChanges":true,"docCount":1,"docStore":[[0,{"fieldLength":1}]],"totalFieldLength":1,"root":{"k":[98],"v":[{"k":[105],"v":[{"k":[111],"v":[{"d":{"df":1,"dc":[[0,1]]}}]}]}]}},"text":{"_store":true,"_optimizeChanges":true,"docCount":1,"docStore":[[0,{"fieldLength":220}]],"totalFieldLength":220,"root":{"k":[96,116,98,100,97,110,115,109,104,105,102,103,117,107,50,99,108,111,112,119,101,106,114],"v":[{"k":[34],"v":[{"k":[111],"v":[{"k":[110],"v":[{"k":[108],"v":[{"k":[121],"v":[{"d":{"df":1,"dc":[[0,1]]}}]}]}]}]}]},{"k":[105,111,104,101],"v":[{"k":[109,99],"v":[{"k":[101],"v":[{"d":{"df":1,"dc":[[0,1]]}}]},{"k":[107],"v":[{"k":[101],"v":[{"k":[116],"v":[{"d":{"df":1,"dc":[[0,1]]}}]}]}]}]},{"d":{"df":1,"dc":[[0,8]]},"k":[111],"v":[{"k":[107],"v":[{"d":{"df":1,"dc":[[0,1]]}}]}]},{"k":[101],"v":[{"d":{"df":1,"dc":[[0,1]]},"k":[115],"v":[{"k":[105],"v":[{"k":[115],"v":[{"d":{"df":1,"dc":[[0,1]]}}]}]}]}]},{"k":[115,99,97],"v":[{"k":[116],"v":[{"d":{"df":1,"dc":[[0,1]]}}]},{"k":[104],"v":[{"k":[110],"v":[{"k":[111],"v":[{"k":[108],"v":[{"k":[111],"v":[{"k":[103],"v":[{"k":[105],"v":[{"k":[101],"v":[{"k":[115],"v":[{"k":[46],"v":[{"d":{"df":1,"dc":[[0,1]]}}]}]}]}]}]}]}]}]}]}]},{"k":[109],"v":[{"d":{"df":1,"dc":[[0,1]]}}]}]}]},{"k":[101,117,111,105],"v":[{"d":{"df":1,"dc":[[0,1]]},"k":[116,99,115],"v":[{"k":[119],"v":[{"k":[101],"v":[{"k":[101],"v":[{"k":[110],"v":[{"d":{"df":1,"dc":[[0,1]]}}]}]}]}]},{"k":[97,111],"v":[{"k":[117],"v":[{"k":[115],"v":[{"k":[101],"v":[{"d":{"df":1,"dc":[[0,1]]}}]}]}]},{"k":[109],"v":[{"k":[101],"v":[{"d":{"df":1,"dc":[[0,1]]}}]}]}]},{"k":[105],"v":[{"k":[100],"v":[{"k":[101],"v":[{"k":[115],"v":[{"d":{"df":1,"dc":[[0,1]]}}]}]}]}]}]},{"k":[116],"v":[{"d":{"df":1,"dc":[[0,3]]}}]},{"k":[117],"v":[{"k":[103],"v":[{"k":[104],"v":[{"k":[116],"v":[{"d":{"df":1,"dc":[[0,1]]}}]}]}]}]},{"k":[103],"v":[{"d":{"df":1,"dc":[[0,1]]}}]}]},{"k":[101,105,117],"v":[{"k":[102,99,103,118],"v":[{"k":[101],"v":[{"k":[97],"v":[{"k":[116],"v":[{"d":{"df":1,"dc":[[0,1]]}}]}]}]},{"k":[105],"v":[{"k":[100],"v":[{"k":[101,105],"v":[{"k":[100],"v":[{"d":{"df":1,"dc":[[0,2]]}}]},{"k":[110],"v":[{"k":[103],"v":[{"d":{"df":1,"dc":[[0,1]]}}]}]}]}]}]},{"k":[114],"v":[{"k":[101],"v":[{"k":[101],"v":[{"d":{"df":1,"dc":[[0,2]]}}]}]}]},{"k":[101],"v":[{"k":[108],"v":[{"k":[111],"v":[{"k":[112],"v":[{"k":[101,105],"v":[{"k":[114],"v":[{"d":{"df":1,"dc":[[0,1]]}}]},{"k":[110],"v":[{"k":[103],"v":[{"k":[44],"v":[{"d":{"df":1,"dc":[[0,1]]}}]}]}]}]}]}]}]}]}]},{"k":[100,102],"v":[{"d":{"df":1,"dc":[[0,1]]}},{"k":[102],"v":[{"k":[101],"v":[{"k":[114],"v":[{"k":[101],"v":[{"k":[110],"v":[{"k":[116],"v":[{"d":{"df":1,"dc":[[0,1]]}}]}]}]}]}]}]}]},{"k":[114],"v":[{"k":[105],"v":[{"k":[110],"v":[{"k":[103],"v":[{"d":{"df":1,"dc":[[0,1]]}}]}]}]}]}]},{"d":{"df":1,"dc":[[0,10]]},"k":[110,108,102,112,103,115,98],"v":[{"k":[100],"v":[{"d":{"df":1,"dc":[[0,6]]},"k":[114],"v":[{"k":[111],"v":[{"k":[105],"v":[{"k":[100],"v":[{"d":{"df":1,"dc":[[0,1]]}}]}]}]}]}]},{"k":[108,119],"v":[{"d":{"df":1,"dc":[[0,1]]}},{"k":[97],"v":[{"k":[121],"v":[{"k":[115],"v":[{"d":{"df":1,"dc":[[0,1]]}}]}]}]}]},{"k":[116],"v":[{"k":[101],"v":[{"k":[114],"v":[{"d":{"df":1,"dc":[[0,1]]}}]}]}]},{"k":[112],"v":[{"k":[108],"v":[{"k":[105],"v":[{"k":[101,99],"v":[{"k":[100],"v":[{"d":{"df":1,"dc":[[0,1]]}}]},{"k":[97],"v":[{"k":[116],"v":[{"k":[105],"v":[{"k":[111],"v":[{"k":[110],"v":[{"d":{"df":1,"dc":[[0,1]]}}]}]}]}]}]}]}]}]}]},{"k":[97],"v":[{"k":[105],"v":[{"k":[110],"v":[{"d":{"df":1,"dc":[[0,1]]}}]}]}]},{"d":{"df":1,"dc":[[0,1]]}},{"k":[111],"v":[{"k":[117],"v":[{"k":[116],"v":[{"d":{"df":1,"dc":[[0,1]]}}]}]}]}]},{"k":[101,97],"v":[{"k":[119,120,116],"v":[{"d":{"df":1,"dc":[[0,4]]}},{"k":[116],"v":[{"d":{"df":1,"dc":[[0,2]]}}]},{"k":[119],"v":[{"k":[111],"v":[{"k":[114],"v":[{"k":[107],"v":[{"k":[115],"v":[{"d":{"df":1,"dc":[[0,1]]}}]}]}]}]}]}]},{"k":[109],"v":[{"k":[101],"v":[{"d":{"df":1,"dc":[[0,1]]}}]}]}]},{"k":[116,97,112,99,111,105],"v":[{"k":[97,101,117],"v":[{"k":[114],"v":[{"k":[116],"v":[{"d":{"df":1,"dc":[[0,1]]},"k":[101],"v":[{"k":[100],"v":[{"d":{"df":1,"dc":[[0,1]]}}]}]}]}]},{"k":[112],"v":[{"k":[46],"v":[{"d":{"df":1,"dc":[[0,1]]}}]}]},{"k":[100],"v":[{"k":[121],"v":[{"k":[44],"v":[{"d":{"df":1,"dc":[[0,1]]}}]}]}]}]},{"k":[118],"v":[{"k":[105],"v":[{"k":[110],"v":[{"k":[103],"v":[{"k":[115],"v":[{"k":[44],"v":[{"d":{"df":1,"dc":[[0,1]]}}]}]}]}]}]}]},{"k":[101],"v":[{"k":[110],"v":[{"k":[100,116],"v":[{"d":{"df":1,"dc":[[0,1]]}},{"d":{"df":1,"dc":[[0,1]]}}]}]}]},{"k":[104],"v":[{"k":[111],"v":[{"k":[111],"v":[{"k":[108],"v":[{"k":[44],"v":[{"d":{"df":1,"dc":[[0,1]]}}]}]}]}]}]},{"d":{"df":1,"dc":[[0,1]]},"k":[102],"v":[{"k":[116],"v":[{"k":[119],"v":[{"k":[97],"v":[{"k":[114],"v":[{"k":[101],"v":[{"d":{"df":1,"dc":[[0,1]]}}]}]}]}]}]}]},{"k":[100],"v":[{"k":[101],"v":[{"k":[44,46],"v":[{"d":{"df":1,"dc":[[0,1]]}},{"d":{"df":1,"dc":[[0,1]]}}]}]}]}]},{"k":[97,121,105,111,101],"v":[{"k":[116],"v":[{"k":[116],"v":[{"k":[101],"v":[{"k":[114],"v":[{"k":[115],"v":[{"k":[34],"v":[{"k":[96],"v":[{"d":{"df":1,"dc":[[0,1]]}}]}]}]}]}]}]}]},{"d":{"df":1,"dc":[[0,12]]}},{"k":[110],"v":[{"k":[100],"v":[{"k":[44],"v":[{"d":{"df":1,"dc":[[0,1]]}}]}]}]},{"k":[110,98],"v":[{"k":[116],"v":[{"k":[104],"v":[{"k":[115],"v":[{"d":{"df":1,"dc":[[0,2]]}}]}]}]},{"k":[105],"v":[{"k":[108],"v":[{"k":[101],"v":[{"d":{"df":1,"dc":[[0,1]]}}]}]}]}]},{"k":[44],"v":[{"d":{"df":1,"dc":[[0,2]]}}]}]},{"k":[101],"v":[{"k":[121,97],"v":[{"k":[44],"v":[{"d":{"df":1,"dc":[[0,1]]}}]},{"k":[114],"v":[{"k":[105],"v":[{"k":[110],"v":[{"k":[103],"v":[{"d":{"df":1,"dc":[[0,1]]}}]}]}]}]}]}]},{"d":{"df":1,"dc":[[0,12]]},"k":[115,108,110,39,116],"v":[{"d":{"df":1,"dc":[[0,1]]}},{"k":[121],"v":[{"k":[97],"v":[{"d":{"df":1,"dc":[[0,1]]}}]}]},{"d":{"df":1,"dc":[[0,11]]},"k":[102,118,116],"v":[{"k":[111],"v":[{"k":[114],"v":[{"k":[109],"v":[{"k":[97],"v":[{"k":[116],"v":[{"k":[105],"v":[{"k":[99],"v":[{"k":[115],"v":[{"k":[44],"v":[{"d":{"df":1,"dc":[[0,1]]}}]}]}]}]}]}]}]}]}]},{"k":[111],"v":[{"k":[108],"v":[{"k":[118],"v":[{"k":[101],"v":[{"k":[100],"v":[{"d":{"df":1,"dc":[[0,1]]}}]}]}]}]}]},{"k":[101],"v":[{"k":[114],"v":[{"k":[101],"v":[{"k":[115],"v":[{"k":[116],"v":[{"k":[105],"v":[{"k":[110],"v":[{"k":[103],"v":[{"d":{"df":1,"dc":[[0,1]]}}]}]}]}]}]}]}]}]}]},{"k":[118,109],"v":[{"k":[101],"v":[{"d":{"df":1,"dc":[[0,2]]}}]},{"d":{"df":1,"dc":[[0,1]]}}]},{"d":{"df":1,"dc":[[0,4]]},"k":[46],"v":[{"d":{"df":1,"dc":[[0,1]]}}]}]},{"k":[97,108,101,105,114,111],"v":[{"k":[107],"v":[{"k":[104],"v":[{"k":[114],"v":[{"k":[117],"v":[{"k":[116],"v":[{"k":[100],"v":[{"k":[105],"v":[{"k":[110],"v":[{"k":[111],"v":[{"k":[118],"v":[{"k":[46],"v":[{"d":{"df":1,"dc":[[0,1]]}}]}]}]}]}]}]}]}]}]}]}]},{"k":[105],"v":[{"k":[103],"v":[{"k":[104],"v":[{"k":[116],"v":[{"d":{"df":1,"dc":[[0,1]]}}]}]}]}]},{"k":[98],"v":[{"k":[114],"v":[{"k":[117],"v":[{"k":[97],"v":[{"k":[114],"v":[{"k":[121],"v":[{"k":[44],"v":[{"d":{"df":1,"dc":[[0,1]]}}]}]}]}]}]}]}]},{"k":[118,114,101],"v":[{"k":[101],"v":[{"d":{"df":1,"dc":[[0,1]]}}]},{"k":[115],"v":[{"k":[116],"v":[{"d":{"df":1,"dc":[[0,2]]}}]}]},{"k":[108],"v":[{"k":[100],"v":[{"k":[44],"v":[{"d":{"df":1,"dc":[[0,1]]}}]}]}]}]},{"k":[111],"v":[{"k":[109],"v":[{"d":{"df":1,"dc":[[0,2]]}}]}]},{"k":[114,117],"v":[{"d":{"df":1,"dc":[[0,4]]}},{"k":[110],"v":[{"k":[100],"v":[{"d":{"df":1,"dc":[[0,1]]}}]}]}]}]},{"k":[114,111,101,117],"v":[{"k":[101,97],"v":[{"k":[119],"v":[{"d":{"df":1,"dc":[[0,1]]}}]},{"k":[100],"v":[{"k":[117],"v":[{"k":[97],"v":[{"k":[116],"v":[{"k":[101],"v":[{"k":[100],"v":[{"d":{"df":1,"dc":[[0,1]]}}]}]}]}]}]}]}]},{"k":[97],"v":[{"k":[108],"v":[{"d":{"df":1,"dc":[[0,1]]}}]}]},{"k":[116],"v":[{"d":{"df":1,"dc":[[0,1]]}}]},{"k":[105],"v":[{"k":[116],"v":[{"k":[97],"v":[{"k":[114],"v":[{"d":{"df":1,"dc":[[0,1]]}}]}]}]}]}]},{"k":[112,115],"v":[{"d":{"df":1,"dc":[[0,1]]}},{"k":[101],"v":[{"d":{"df":1,"dc":[[0,1]]}}]}]},{"k":[97,110,111],"v":[{"k":[122],"v":[{"k":[97],"v":[{"k":[107],"v":[{"k":[104],"v":[{"k":[115],"v":[{"k":[116],"v":[{"k":[97],"v":[{"k":[110],"v":[{"k":[44],"v":[{"d":{"df":1,"dc":[[0,1]]}}]}]}]}]}]}]}]}]}]},{"k":[111],"v":[{"k":[119],"v":[{"k":[108],"v":[{"k":[101],"v":[{"k":[100],"v":[{"k":[103],"v":[{"k":[101],"v":[{"k":[44],"v":[{"d":{"df":1,"dc":[[0,1]]}}]}]}]}]}]}]}]}]},{"k":[116],"v":[{"k":[108],"v":[{"k":[105],"v":[{"k":[110],"v":[{"k":[46],"v":[{"d":{"df":1,"dc":[[0,1]]}}]}]}]}]}]}]},{"k":[48],"v":[{"k":[49],"v":[{"k":[53,54,57],"v":[{"d":{"df":1,"dc":[[0,1]]}},{"k":[44],"v":[{"d":{"df":1,"dc":[[0,2]]}}]},{"d":{"df":1,"dc":[[0,1]]}}]}]}]},{"k":[104,122,111,114,97],"v":[{"k":[97,111],"v":[{"k":[110,108],"v":[{"k":[103],"v":[{"k":[101],"v":[{"d":{"df":1,"dc":[[0,1]]}}]}]},{"k":[108],"v":[{"k":[101],"v":[{"k":[110],"v":[{"k":[103],"v":[{"k":[101],"v":[{"d":{"df":1,"dc":[[0,1]]},"k":[46],"v":[{"d":{"df":1,"dc":[[0,1]]}}]}]}]}]}]}]}]},{"k":[111],"v":[{"k":[115],"v":[{"k":[101],"v":[{"d":{"df":1,"dc":[[0,1]]}}]}]}]}]},{"k":[101],"v":[{"k":[99],"v":[{"k":[104],"v":[{"d":{"df":1,"dc":[[0,2]]}}]}]}]},{"k":[117,108],"v":[{"k":[112],"v":[{"k":[108],"v":[{"k":[101],"v":[{"d":{"df":1,"dc":[[0,1]]}}]}]}]},{"k":[108],"v":[{"k":[101],"v":[{"k":[103],"v":[{"k":[101],"v":[{"d":{"df":1,"dc":[[0,1]]}}]}]}]}]}]},{"k":[101],"v":[{"k":[97],"v":[{"k":[116],"v":[{"k":[105],"v":[{"k":[111],"v":[{"k":[110],"v":[{"d":{"df":1,"dc":[[0,1]]}}]}]}]}]}]}]},{"k":[110],"v":[{"d":{"df":1,"dc":[[0,1]]}}]}]},{"k":[105,101,97],"v":[{"k":[102,107],"v":[{"k":[101],"v":[{"k":[46],"v":[{"d":{"df":1,"dc":[[0,1]]}}]}]},{"k":[101],"v":[{"d":{"df":1,"dc":[[0,2]]}}]}]},{"k":[97],"v":[{"k":[114],"v":[{"k":[110],"v":[{"d":{"df":1,"dc":[[0,3]]},"k":[105],"v":[{"k":[110],"v":[{"k":[103],"v":[{"k":[46],"v":[{"d":{"df":1,"dc":[[0,1]]}}]}]}]}]}]}]}]},{"k":[110],"v":[{"k":[103],"v":[{"k":[117],"v":[{"k":[97],"v":[{"k":[103],"v":[{"k":[101],"v":[{"d":{"df":1,"dc":[[0,3]]},"k":[46],"v":[{"d":{"df":1,"dc":[[0,1]]}}]}]}]}]}]}]}]}]},{"k":[110,102],"v":[{"d":{"df":1,"dc":[[0,2]]},"k":[101,108],"v":[{"d":{"df":1,"dc":[[0,1]]},"k":[45],"v":[{"k":[119],"v":[{"k":[97],"v":[{"k":[121],"v":[{"d":{"df":1,"dc":[[0,1]]}}]}]}]}]},{"k":[121],"v":[{"d":{"df":1,"dc":[[0,1]]}}]}]},{"d":{"df":1,"dc":[[0,3]]}}]},{"k":[114,111,108,97],"v":[{"k":[97,111],"v":[{"k":[103],"v":[{"k":[117],"v":[{"k":[101],"v":[{"k":[46],"v":[{"d":{"df":1,"dc":[[0,1]]}}]}]}]}]},{"k":[103,106],"v":[{"k":[114],"v":[{"k":[97],"v":[{"k":[109],"v":[{"k":[109],"v":[{"k":[101],"v":[{"k":[100],"v":[{"d":{"df":1,"dc":[[0,1]]}}]}]}]}]}]}]},{"k":[101],"v":[{"k":[99],"v":[{"k":[116],"v":[{"k":[115],"v":[{"k":[44],"v":[{"d":{"df":1,"dc":[[0,1]]}}]}]}]}]}]}]}]},{"k":[108],"v":[{"k":[121],"v":[{"k":[116],"v":[{"k":[101],"v":[{"k":[99],"v":[{"k":[104],"v":[{"k":[110],"v":[{"k":[105],"v":[{"k":[99],"v":[{"k":[115],"v":[{"d":{"df":1,"dc":[[0,1]]}}]}]}]}]}]}]}]}]}]}]},{"k":[97],"v":[{"k":[116,121],"v":[{"k":[102],"v":[{"k":[111],"v":[{"k":[114],"v":[{"k":[109],"v":[{"k":[44],"v":[{"d":{"df":1,"dc":[[0,1]]}}]}]}]}]}]},{"d":{"df":1,"dc":[[0,1]]},"k":[101],"v":[{"k":[114],"v":[{"k":[44],"v":[{"d":{"df":1,"dc":[[0,1]]}}]}]}]}]}]},{"k":[115],"v":[{"k":[115],"v":[{"k":[105],"v":[{"k":[111],"v":[{"k":[110],"v":[{"d":{"df":1,"dc":[[0,1]]},"k":[46],"v":[{"d":{"df":1,"dc":[[0,1]]}}]}]}]}]}]}]}]},{"k":[105,97,101,104,111],"v":[{"k":[116],"v":[{"k":[104],"v":[{"d":{"df":1,"dc":[[0,1]]}}]}]},{"k":[115],"v":[{"d":{"df":1,"dc":[[0,3]]}}]},{"k":[98],"v":[{"d":{"df":1,"dc":[[0,1]]}}]},{"k":[101],"v":[{"k":[114],"v":[{"k":[101],"v":[{"d":{"df":1,"dc":[[0,1]]}}]}]}]},{"k":[114],"v":[{"k":[107],"v":[{"k":[46],"v":[{"d":{"df":1,"dc":[[0,1]]}}]}]}]}]},{"k":[110],"v":[{"k":[104],"v":[{"k":[97],"v":[{"k":[110],"v":[{"k":[99],"v":[{"k":[101],"v":[{"d":{"df":1,"dc":[[0,1]]}}]}]}]}]}]}]},{"k":[105,111],"v":[{"k":[104],"v":[{"k":[108],"v":[{"k":[97],"v":[{"k":[118],"v":[{"k":[97],"v":[{"k":[44],"v":[{"d":{"df":1,"dc":[[0,1]]}}]}]}]}]}]}]},{"k":[98],"v":[{"d":{"df":1,"dc":[[0,1]]}}]}]},{"k":[101,117],"v":[{"k":[112,97],"v":[{"k":[117],"v":[{"k":[98],"v":[{"k":[108],"v":[{"k":[105],"v":[{"k":[99],"v":[{"k":[46],"v":[{"d":{"df":1,"dc":[[0,1]]}}]}]}]}]}]}]},{"k":[108,100],"v":[{"k":[108],"v":[{"k":[121],"v":[{"d":{"df":1,"dc":[[0,1]]}}]}]},{"k":[44],"v":[{"d":{"df":1,"dc":[[0,1]]}}]}]}]},{"k":[110],"v":[{"k":[46],"v":[{"d":{"df":1,"dc":[[0,1]]}}]}]}]}]}}}}}],"databaseVersion":1.5,"engineVersion":1.5,"filename":"content.db","_persistenceAdapter":null,"_persistenceMethod":null,"_throttledSaves":true}